./.gitignore
./LICENSE
./PKG-INFO
./README.md
./pyproject.toml
./.github/FUNDING.yml
./.github/workflows/python-publish.yml
./django_text_translator/__init__.py
./django_text_translator/admin.py
./django_text_translator/apps.py
./django_text_translator/tests.py
./django_text_translator/views.py
./django_text_translator/migrations/0001_initial.py
./django_text_translator/migrations/0002_openaitranslator_base_url_and_more.py
./django_text_translator/migrations/0003_azureaitranslator_openaitranslator_frequency_penalty_and_more.py
./django_text_translator/migrations/0004_alter_openaitranslator_model.py
./django_text_translator/migrations/0005_caiyuntranslator_deeplxtranslator.py
./django_text_translator/migrations/0006_testtranslator_alter_openaitranslator_prompt.py
./django_text_translator/migrations/0007_caiyuntranslator_max_characters_and_more.py
./django_text_translator/migrations/0008_geminitranslator.py
./django_text_translator/migrations/0009_deepltranslator_proxy_deepltranslator_server_url.py
./django_text_translator/migrations/0010_claudetranslator.py
./django_text_translator/migrations/0011_googletranslatewebtranslator_and_more.py
./django_text_translator/migrations/0012_geminitranslator_interval.py
./django_text_translator/migrations/0013_deeplwebtranslator.py
./django_text_translator/migrations/0014_testtranslator_interval.py
./django_text_translator/migrations/0015_googletranslatewebtranslator_max_characters.py
./django_text_translator/migrations/0016_alter_deeplwebtranslator_max_characters_and_more.py
./django_text_translator/migrations/0017_remove_translated_content_id_and_more.py
./django_text_translator/migrations/0018_alter_claudetranslator_model.py
./django_text_translator/migrations/0019_alter_openaitranslator_model.py
./django_text_translator/migrations/0020_moonshotaitranslator.py
./django_text_translator/migrations/0021_alter_claudetranslator_model.py
./django_text_translator/migrations/0022_alter_geminitranslator_model.py
django_text_translator-2024.5.1.dist-info/METADATA
django_text_translator-2024.5.1.dist-info/WHEEL
django_text_translator-2024.5.1.dist-info/licenses/LICENSE
django_text_translator-2024.5.1.dist-info/RECORD
