Metadata-Version: 2.3
Name: django-text-translator
Version: 2024.5.1
Summary: A Django application that supports adding multiple third-party engines for text translation.
Project-URL: Homepage, https://github.com/rss-translator/django-text-translator
Project-URL: Repository, https://github.com/rss-translator/django-text-translator.git
Project-URL: Issues, https://github.com/rss-translator/django-text-translator/issues
Author-email: Versun <django-text-translator@versun.me>
License: MIT License
License-File: LICENSE
Classifier: Environment :: Web Environment
Classifier: Framework :: Django
Classifier: Framework :: Django :: 5.0
Classifier: Intended Audience :: Developers
Classifier: License :: OSI Approved :: MIT License
Classifier: Operating System :: OS Independent
Classifier: Programming Language :: Python
Classifier: Programming Language :: Python :: 3
Classifier: Programming Language :: Python :: 3 :: Only
Classifier: Programming Language :: Python :: 3.10
Classifier: Programming Language :: Python :: 3.11
Classifier: Programming Language :: Python :: 3.12
Classifier: Topic :: Internet :: WWW/HTTP
Classifier: Topic :: Internet :: WWW/HTTP :: Dynamic Content
Classifier: Topic :: Software Development :: Libraries :: Application Frameworks
Classifier: Topic :: Software Development :: Libraries :: Python Modules
Requires-Python: >=3.10
Requires-Dist: anthropic>=0.18.1
Requires-Dist: cityhash>=0.4.7
Requires-Dist: deepl>=1.17.0
Requires-Dist: django-encrypted-model-fields>=0.6.5
Requires-Dist: django>=5.0.2
Requires-Dist: google-generativeai>=0.5.1
Requires-Dist: httpx>=0.27.0
Requires-Dist: openai>=1.12.0
Requires-Dist: pydeeplx>=1.0.7
